patha_svarantaranam/__init__.py
patha_svarantaranam/tts.py
patha_svarantaranam-10.0.0.0.0.dist-info/LICENSE
patha_svarantaranam-10.0.0.0.0.dist-info/METADATA
patha_svarantaranam-10.0.0.0.0.dist-info/WHEEL
patha_svarantaranam-10.0.0.0.0.dist-info/top_level.txt
patha_svarantaranam-10.0.0.0.0.dist-info/RECORD
