Metadata-Version: 2.1
Name: patha_svarantaranam
Version: 10.0.0.0.0
Summary: A Python module for text-to-speech conversion using the Pāṭha-Svarāntaraṇam API
Home-page: https://github.com/sandeshaiplus/patha-svarantaranam
Author: sandesh kumar
Author-email: support@sandeshai.in
Classifier: Development Status :: 3 - Alpha
Classifier: Intended Audience :: Developers
Classifier: License :: OSI Approved :: MIT License
Classifier: Operating System :: OS Independent
Classifier: Programming Language :: Python :: 3
Classifier: Programming Language :: Python :: 3.6
Classifier: Programming Language :: Python :: 3.7
Classifier: Programming Language :: Python :: 3.8
Classifier: Programming Language :: Python :: 3.9
Requires-Python: >=3.6
License-File: LICENSE
Requires-Dist: requests
Requires-Dist: playsound
Requires-Dist: colorama
